{"skeleton":{"hash":"dC/11DhGm0EfxeKBf19GKS9a7YM","spine":"3.8.99"},"bones":[{"name":"root"},{"name":"bomb2","parent":"root","scaleX":0.35,"scaleY":0.35}],"slots":[{"name":"a1","bone":"bomb2"}],"skins":[{"name":"default","attachments":{"a1":{"a1":{"x":0.5,"width":109,"height":96},"a2":{"width":160,"height":152},"a3":{"width":188,"height":176},"a4":{"width":188,"height":178},"a5":{"width":190,"height":188},"a6":{"width":202,"height":196},"a7":{"width":194,"height":194},"a8":{"width":192,"height":192},"a9":{"x":0.5,"width":191,"height":192}}}}],"animations":{"spaceship_bomb2":{"slots":{"a1":{"attachment":[{"name":"a1"},{"time":0.0667,"name":"a2"},{"time":0.1333,"name":"a3"},{"time":0.2,"name":"a4"},{"time":0.2667,"name":"a5"},{"time":0.3333,"name":"a6"},{"time":0.4,"name":"a7"},{"time":0.4667,"name":"a8"},{"time":0.5333,"name":"a9"},{"time":0.6,"name":null}]}}}}}